peng3dnet/__init__.py
peng3dnet/conntypes.py
peng3dnet/constants.py
peng3dnet/errors.py
peng3dnet/net.py
peng3dnet/registry.py
peng3dnet/util.py
peng3dnet/version.py
peng3dnet/ext/__init__.py
peng3dnet/ext/mpgame.py
peng3dnet/ext/ping.py
peng3dnet/packet/__init__.py
peng3dnet/packet/internal.py
peng3dnet-0.1.3a0.dist-info/LICENSE.md
peng3dnet-0.1.3a0.dist-info/METADATA
peng3dnet-0.1.3a0.dist-info/WHEEL
peng3dnet-0.1.3a0.dist-info/top_level.txt
peng3dnet-0.1.3a0.dist-info/RECORD
